ezapidata/__init__.py
ezapidata/__main__.py
ezapidata/main.py
ezapidata/ApiList/__init__.py
ezapidata/ApiList/dailyuseapi/__init__.py
ezapidata/ApiList/dailyuseapi/weather.py
ezapidata/ApiList/games/Brawl_Stars.py
ezapidata/ApiList/games/__init__.py
EzApiData-0.1.3.2.dist-info/LICENSE
EzApiData-0.1.3.2.dist-info/METADATA
EzApiData-0.1.3.2.dist-info/WHEEL
EzApiData-0.1.3.2.dist-info/top_level.txt
EzApiData-0.1.3.2.dist-info/RECORD
