Metadata-Version: 2.1
Name: EzApiData
Version: 0.1.3.2
Summary: Get data from api easier
Home-page: UNKNOWN
Author: Ruthle55 (Thaddeus Teo)
Author-email: <ruthle55.enquiries@gmail.com>
License: UNKNOWN
Keywords: python,Games,Data,Game data
Platform: UNKNOWN
Classifier: Development Status :: 1 - Planning
Classifier: Intended Audience :: Developers
Classifier: Programming Language :: Python :: 3
Classifier: Operating System :: Unix
Classifier: Operating System :: MacOS :: MacOS X
Classifier: Operating System :: Microsoft :: Windows
License-File: LICENSE
Requires-Dist: requests (>=2.25.0)
Requires-Dist: typing (>=3.7.4)
